MANIFEST.in
README.md
setup.cfg
setup.py
Examples/client_shell.py
Examples/quick_setup_client.py
Examples/quick_setup_server.py
Examples/server_shell.py
MultiSC/make_multi.py
MultiSC.egg-info/PKG-INFO
MultiSC.egg-info/SOURCES.txt
MultiSC.egg-info/dependency_links.txt
MultiSC.egg-info/entry_points.txt
MultiSC.egg-info/requires.txt
MultiSC.egg-info/top_level.txt
MultiSC/Examples/simple_client.py
MultiSC/Examples/simple_quick_server.py
MultiSC/Examples/simple_server.py
MultiSC/Examples/protocols/groups.py
MultiSC/Examples/protocols/user_protocol.py
MultiSC/MultiClient/DNSClient.py
MultiSC/MultiClient/EasyClient.py
MultiSC/MultiClient/__init__.py
MultiSC/MultiClient/client.py
MultiSC/MultiClient/secure_connection.py
MultiSC/MultiClient/__client_config__/connection_config.py
MultiSC/MultiClient/__client_config__/dns_config.py
MultiSC/MultiClient/__client_config__/public_verify_key.rsa
MultiSC/MultiClient/__client_config__/security_config.py
MultiSC/MultiServer/__init__.py
MultiSC/MultiServer/run.py
MultiSC/MultiServer/ConnectionsHandler/RequestHandler.py
MultiSC/MultiServer/ConnectionsHandler/server.py
MultiSC/MultiServer/DB/AbsDb.py
MultiSC/MultiServer/DB/MongoDbAPI.py
MultiSC/MultiServer/DB/TempDB.py
MultiSC/MultiServer/DB/__init__.py
MultiSC/MultiServer/Exceptions/CloseConnection.py
MultiSC/MultiServer/Exceptions/ExceptionHandler.py
MultiSC/MultiServer/Exceptions/MainException.py
MultiSC/MultiServer/Exceptions/QueryKeyError.py
MultiSC/MultiServer/Exceptions/TestException.py
MultiSC/MultiServer/Exceptions/__init__.py
MultiSC/MultiServer/Handlers/catch_events_handler.py
MultiSC/MultiServer/Handlers/signals_handler.py
MultiSC/MultiServer/__config__/companys_config.py
MultiSC/MultiServer/__config__/db_config.py
MultiSC/MultiServer/__config__/logging_config.py
MultiSC/MultiServer/__config__/monitors_config.py
MultiSC/MultiServer/__config__/protocol_code_config.py
MultiSC/MultiServer/__config__/request_handler_config.py
MultiSC/MultiServer/__config__/security_config.py
MultiSC/MultiServer/__config__/server_config.py
MultiSC/MultiServer/__config__/system_config.py
MultiSC/MultiServer/__config__/users_config.py
