Metadata-Version: 2.1
Name: MultiSC
Version: 0.0.12
Summary: Server and client for your app needs
Home-page: https://github.com/hvuhsg/MultiSC
Author: Yehoyada.s
Author-email: hvuhsg6@gmail.com
License: MIT
Download-URL: https://github.com/hvuhsg/MultiSC/archive/v0.0.12.tar.gz
Keywords: Server,Client,Easy,app,client,server
Platform: UNKNOWN
Classifier: Development Status :: 3 - Alpha
Classifier: Intended Audience :: Developers
Classifier: Topic :: Software Development :: Build Tools
Classifier: License :: OSI Approved :: MIT License
Classifier: Programming Language :: Python :: 3
Classifier: Programming Language :: Python :: 3.6
Classifier: Programming Language :: Python :: 3.7
